godot_universal_spritepacker/__init__.py
godot_universal_spritepacker/godot_universal_spritepacker.py
godot_universal_spritepacker-1.1.8.dist-info/licenses/LICENSE
godot_universal_spritepacker-1.1.8.dist-info/METADATA
godot_universal_spritepacker-1.1.8.dist-info/WHEEL
godot_universal_spritepacker-1.1.8.dist-info/entry_points.txt
godot_universal_spritepacker-1.1.8.dist-info/top_level.txt
godot_universal_spritepacker-1.1.8.dist-info/RECORD
