Metadata-Version: 2.4
Name: godot-universal-spritepacker
Version: 1.1.8
Summary: A smart, folder-aware sprite packer for Godot and PixiJS. Split, pack, and convert multi-res tilesets and SVG layers into spritesheets and native Godot sprites.
Author: Donitz
License-Expression: MIT
Project-URL: Homepage, https://github.com/Donitzo/godot-universal-spritepacker
Classifier: Programming Language :: Python :: 3.9
Classifier: Programming Language :: Python :: 3.10
Classifier: Programming Language :: Python :: 3.11
Classifier: Operating System :: OS Independent
Classifier: Topic :: Multimedia :: Graphics
Requires-Python: >=3.9
License-File: LICENSE
Requires-Dist: Pillow
Requires-Dist: rectpack
Dynamic: license-file
